.readthedocs.yml
LICENSE
README.md
pyproject.toml
pytest.ini
setup.py
docs/Makefile
docs/source/conf.py
docs/source/exceptions.rst
docs/source/index.rst
docs/source/openvpn_config.rst
docs/source/openvpn_server.rst
src/openvpn_server/__init__.py
src/openvpn_server/exceptions.py
src/openvpn_server/openvpn_server.py
src/openvpn_server.egg-info/PKG-INFO
src/openvpn_server.egg-info/SOURCES.txt
src/openvpn_server.egg-info/dependency_links.txt
src/openvpn_server.egg-info/requires.txt
src/openvpn_server.egg-info/top_level.txt
tests/conf/server.conf
tests/conf/keys/ca.crt
tests/conf/keys/client1.crt
tests/conf/keys/client1.key
tests/conf/keys/dh2048.pem
tests/conf/keys/server.crt
tests/conf/keys/server.key