Metadata-Version: 2.1
Name: openvpn-server
Version: 0.1.0
Summary: Python package for managing OpenVPN instances through their entire life cycle
Home-page: https://gitlab.com/D0han/openvpn-server
Author: Piotr Szczepaniak
Author-email: szczep.piotr+openvpn-server@gmail.com
License: UNKNOWN
Project-URL: Bug Tracker, https://gitlab.com/D0han/openvpn-server/-/issues
Project-URL: Source, https://gitlab.com/D0han/openvpn-server/-/tree/master
Project-URL: Documentation, https://openvpn-server.readthedocs.io/en/stable/
Keywords: openvpn,management
Platform: UNKNOWN
Classifier: Development Status :: 4 - Beta
Classifier: Intended Audience :: Developers
Classifier: Intended Audience :: System Administrators
Classifier: License :: OSI Approved :: MIT License
Classifier: Operating System :: POSIX :: Linux
Classifier: Programming Language :: Python :: 3
Classifier: Programming Language :: Python :: 3.6
Classifier: Programming Language :: Python :: 3.7
Classifier: Programming Language :: Python :: 3.8
Classifier: Programming Language :: Python :: Implementation :: CPython
Classifier: Topic :: Internet
Classifier: Topic :: Software Development :: Libraries :: Python Modules
Classifier: Topic :: Security
Classifier: Topic :: System :: Networking
Requires-Python: >=3.6.0
Provides-Extra: dev
Provides-Extra: testing
Provides-Extra: docs
